Typhon/RCE_data.py
Typhon/Typhon.py
Typhon/__init__.py
Typhon/bypasser.py
Typhon/utils.py
typhonbreaker-1.0.11.2.dist-info/licenses/LICENSE.txt
typhonbreaker-1.0.11.2.dist-info/METADATA
typhonbreaker-1.0.11.2.dist-info/WHEEL
typhonbreaker-1.0.11.2.dist-info/top_level.txt
typhonbreaker-1.0.11.2.dist-info/RECORD
