Metadata-Version: 2.4
Name: typhonbreaker
Version: 1.0.11.2
Summary: A auto pyjail (python sandbox) solver
Home-page: https://github.com/Team-intN18-SoybeanSeclab/Typhon
Author: LamentXU(Weilin Du)
Author-email: lamentxu644@gmail.com
License: Apache-2.0
Project-URL: Documentation, https://typhon.lamentxu.top
Classifier: Programming Language :: Python
Classifier: Programming Language :: Python :: 3
Classifier: Programming Language :: Python :: 3.9
Classifier: Programming Language :: Python :: 3.10
Classifier: Programming Language :: Python :: 3.11
Classifier: Programming Language :: Python :: 3.12
Classifier: Programming Language :: Python :: 3.13
Classifier: Programming Language :: Python :: 3.14
Classifier: Programming Language :: Python :: Implementation :: CPython
Classifier: Natural Language :: Chinese (Simplified)
Requires-Python: >=3.9.0
License-File: LICENSE.txt
Dynamic: author
Dynamic: author-email
Dynamic: classifier
Dynamic: description
Dynamic: description-content-type
Dynamic: home-page
Dynamic: license
Dynamic: license-file
Dynamic: project-url
Dynamic: requires-python
Dynamic: summary
